stadincijfers/__init__.py
stadincijfers/_stadincijfers.py
stadincijfers-0.2.3.dist-info/licenses/LICENSE
stadincijfers-0.2.3.dist-info/METADATA
stadincijfers-0.2.3.dist-info/WHEEL
stadincijfers-0.2.3.dist-info/top_level.txt
stadincijfers-0.2.3.dist-info/RECORD
