Metadata-Version: 2.4
Name: stadincijfers
Version: 0.2.3
Summary: A python package to make data from stadincijfers easily available for data scientists. 
Home-page: https://github.com/Team-Data-Antwerpen/stadincijfers.py
Author: Kay Warrie, Sofie Cromheeke
Author-email: kaywarrie@gmail.com, sofie.cromheeke@gmail.com
Classifier: Programming Language :: Python :: 3
Classifier: License :: OSI Approved :: MIT License
Classifier: Operating System :: OS Independent
Requires-Python: >=2.7
License-File: LICENSE
Requires-Dist: pandas
Dynamic: author
Dynamic: author-email
Dynamic: classifier
Dynamic: description
Dynamic: description-content-type
Dynamic: home-page
Dynamic: license-file
Dynamic: requires-dist
Dynamic: requires-python
Dynamic: summary
